claix/__init__.py
claix/__main__.py
claix/ai.py
claix/main.py
claix/typer_utils.py
claix/utils.py
claix-0.1.6.dist-info/METADATA
claix-0.1.6.dist-info/WHEEL
claix-0.1.6.dist-info/entry_points.txt
claix-0.1.6.dist-info/RECORD
