Metadata-Version: 2.1
Name: claix
Version: 0.1.6
Summary: A CLI translating user requests into specific CLI commands
Author: Facundo Goiriz
Author-email: facundogoiriz@gmail.com
Requires-Python: >=3.10,<4.0
Classifier: Programming Language :: Python :: 3
Classifier: Programming Language :: Python :: 3.10
Classifier: Programming Language :: Python :: 3.11
Classifier: Programming Language :: Python :: 3.12
Classifier: Programming Language :: Python :: 3.13
Requires-Dist: inquirer (>=3.1.4,<4.0.0)
Requires-Dist: instructor (>=1.5.2,<2.0.0)
Requires-Dist: openai (>=1.45.0,<2.0.0)
Requires-Dist: typer[all] (>=0.9.0,<0.10.0)
